guillotina_pgcatalog/__init__.py
guillotina_pgcatalog/api.py
guillotina_pgcatalog/schema.py
guillotina_pgcatalog/utility.py
guillotina_pgcatalog/tests/__init__.py
guillotina_pgcatalog/tests/conftest.py
guillotina_pgcatalog/tests/fixtures.py
guillotina_pgcatalog/tests/test_search.py
guillotina_pgcatalog-1.0.7.dist-info/METADATA
guillotina_pgcatalog-1.0.7.dist-info/RECORD
guillotina_pgcatalog-1.0.7.dist-info/WHEEL
guillotina_pgcatalog-1.0.7.dist-info/top_level.txt
guillotina_pgcatalog-1.0.7.dist-info/zip-safe
