Metadata-Version: 2.1
Name: guillotina-pgcatalog
Version: 1.0.7
Summary: basic catalog implementation for guillotina on postgres
Home-page: UNKNOWN
Author: Nathan Van Gheem
Author-email: vangheem@gmail.com
License: private
Keywords: asyncio,REST,Framework,transactional
Platform: UNKNOWN
Classifier: License :: OSI Approved :: BSD License
Classifier: Development Status :: 3 - Alpha
Classifier: Intended Audience :: Developers
Classifier: Topic :: Internet :: WWW/HTTP
Classifier: Programming Language :: Python :: 3.6
Classifier: Topic :: Software Development :: Libraries :: Python Modules
Provides-Extra: test
Requires-Dist: guillotina (>=4.5.0)
Provides-Extra: test
Requires-Dist: pytest; extra == 'test'
Requires-Dist: requests; extra == 'test'
Requires-Dist: docker; extra == 'test'
Requires-Dist: backoff; extra == 'test'
Requires-Dist: requests; extra == 'test'
Requires-Dist: psycopg2; extra == 'test'
Requires-Dist: pytest-asyncio; extra == 'test'
Requires-Dist: pytest-aiohttp; extra == 'test'
Requires-Dist: pytest-docker-fixtures; extra == 'test'
